nyckel/__init__.py
nyckel/auth.py
nyckel/config.py
nyckel/data_classes.py
nyckel/image_processing.py
nyckel/py.typed
nyckel/request_utils.py
nyckel/utils.py
nyckel/functions/__init__.py
nyckel/functions/pretrained.py
nyckel/functions/utils.py
nyckel/functions/classification/__init__.py
nyckel/functions/classification/classification.py
nyckel/functions/classification/factory.py
nyckel/functions/classification/function_handler.py
nyckel/functions/classification/image_classification.py
nyckel/functions/classification/label_handler.py
nyckel/functions/classification/sample_handler.py
nyckel/functions/classification/tabular_classification.py
nyckel/functions/classification/text_classification.py
nyckel/functions/tags/__init__.py
nyckel/functions/tags/image_tags.py
nyckel/functions/tags/tabular_tags.py
nyckel/functions/tags/tags.py
nyckel/functions/tags/tags_function_factory.py
nyckel/functions/tags/tags_function_handler.py
nyckel/functions/tags/tags_sample_handler.py
nyckel/functions/tags/text_tags.py
nyckel-0.4.23.dist-info/METADATA
nyckel-0.4.23.dist-info/WHEEL
nyckel-0.4.23.dist-info/licenses/LICENSE
nyckel-0.4.23.dist-info/RECORD
