Metadata-Version: 2.4
Name: nyckel
Version: 0.4.23
Summary: Python package for the Nyckel API
Project-URL: Homepage, https://github.com/NyckelAI/python-sdk
Author-email: Oscar Beijbom <oscar@nyckel.com>
License-File: LICENSE
Classifier: License :: OSI Approved :: MIT License
Classifier: Operating System :: OS Independent
Classifier: Programming Language :: Python :: 3
Requires-Python: >=3.8
Requires-Dist: pillow-avif-plugin>=1.4
Requires-Dist: pillow>=8.0.0
Requires-Dist: requests>=2.10.0
Requires-Dist: tqdm>=4.0.0
